context_manager/__init__.py
context_manager-0.1.0.dist-info/METADATA
context_manager-0.1.0.dist-info/WHEEL
context_manager-0.1.0.dist-info/RECORD
